heyy/__init__.py
heyy/__version__.py
heyy/core.py
heyy/pathtool.py
heyy/types.py
heyy/utils.py
heyy-0.4.2.dist-info/LICENSE
heyy-0.4.2.dist-info/METADATA
heyy-0.4.2.dist-info/WHEEL
heyy-0.4.2.dist-info/top_level.txt
heyy-0.4.2.dist-info/RECORD
