Metadata-Version: 2.1
Name: heyy
Version: 0.4.2
Summary: Some simple utilities.
Home-page: https://github.com/CarlHey/heyy
Author: heyy
Author-email: hey.ing@qq.com
License: MIT
Platform: UNKNOWN
Classifier: License :: OSI Approved :: MIT License
Classifier: Programming Language :: Python
Classifier: Programming Language :: Python :: 3
Classifier: Programming Language :: Python :: 3.6
Classifier: Programming Language :: Python :: Implementation :: CPython
Classifier: Programming Language :: Python :: Implementation :: PyPy
Requires-Python: >=3.6.0
